jasp/__init__.py
jasp-0.0.0.dist-info/METADATA
jasp-0.0.0.dist-info/WHEEL
jasp-0.0.0.dist-info/top_level.txt
jasp-0.0.0.dist-info/RECORD
